tildee/__init__.py
tildee/models.py
tildee-0.6.1.dist-info/LICENSE
tildee-0.6.1.dist-info/WHEEL
tildee-0.6.1.dist-info/METADATA
tildee-0.6.1.dist-info/RECORD
