Metadata-Version: 2.1
Name: tildee
Version: 0.6.1
Summary: A client for tildes.net
Home-page: https://tildee.readthedocs.io/en/latest/index.html
License: MIT
Author: deing
Author-email: admin@15318.de
Requires-Python: >=3.7,<4.0
Classifier: License :: OSI Approved :: MIT License
Classifier: Operating System :: OS Independent
Classifier: Programming Language :: Python :: 3
Classifier: Programming Language :: Python :: 3.7
Classifier: Programming Language :: Python :: 3.8
Classifier: Topic :: Internet :: WWW/HTTP
Requires-Dist: cssselect (>=1.0,<2.0)
Requires-Dist: lxml (>=4.3,<5.0)
Requires-Dist: requests (>=2.22,<3.0)
Project-URL: Repository, https://git.dingenskirchen.systems/Dingens/tildee.py
